CHANGES.rst
MANIFEST.in
README.rst
setup.cfg
setup.py
Products/__init__.py
Products.Doormat.egg-info/PKG-INFO
Products.Doormat.egg-info/SOURCES.txt
Products.Doormat.egg-info/dependency_links.txt
Products.Doormat.egg-info/entry_points.txt
Products.Doormat.egg-info/namespace_packages.txt
Products.Doormat.egg-info/not-zip-safe
Products.Doormat.egg-info/requires.txt
Products.Doormat.egg-info/top_level.txt
Products/Doormat/__init__.py
Products/Doormat/config.py
Products/Doormat/configure.zcml
Products/Doormat/profiles.zcml
Products/Doormat/setuphandlers.py
Products/Doormat/testing.py
Products/Doormat/Extensions/Install.py
Products/Doormat/browser/__init__.py
Products/Doormat/browser/configure.zcml
Products/Doormat/browser/doormat_bare_view.pt
Products/Doormat/browser/doormat_view.pt
Products/Doormat/browser/doormat_viewlet.pt
Products/Doormat/browser/doormat_viewlet_bare.pt
Products/Doormat/browser/interfaces.py
Products/Doormat/browser/macros.pt
Products/Doormat/browser/views.py
Products/Doormat/browser/stylesheets/doormat.css
Products/Doormat/content/Doormat.py
Products/Doormat/content/DoormatCollection.py
Products/Doormat/content/DoormatColumn.py
Products/Doormat/content/DoormatMixin.py
Products/Doormat/content/DoormatReference.py
Products/Doormat/content/DoormatSection.py
Products/Doormat/content/__init__.py
Products/Doormat/content/interfaces.py
Products/Doormat/i18n/generated.pot
Products/Doormat/locales/Doormat-manual.pot
Products/Doormat/locales/Doormat.pot
Products/Doormat/locales/NOTEMPTY.txt
Products/Doormat/locales/plone.pot
Products/Doormat/locales/rebuild.sh
Products/Doormat/locales/es/LC_MESSAGES/Doormat.mo
Products/Doormat/locales/es/LC_MESSAGES/Doormat.po
Products/Doormat/locales/es/LC_MESSAGES/plone.mo
Products/Doormat/locales/es/LC_MESSAGES/plone.po
Products/Doormat/profiles/default/Doormat_marker.txt
Products/Doormat/profiles/default/browserlayer.xml
Products/Doormat/profiles/default/catalog.xml
Products/Doormat/profiles/default/cssregistry.xml
Products/Doormat/profiles/default/factorytool.xml
Products/Doormat/profiles/default/import_steps.xml
Products/Doormat/profiles/default/metadata.xml
Products/Doormat/profiles/default/skins.xml
Products/Doormat/profiles/default/types.xml
Products/Doormat/profiles/default/viewlets.xml
Products/Doormat/profiles/default/types/Doormat.xml
