Metadata-Version: 1.1
Name: Products.Doormat
Version: 1.2
Summary: Adds a doormat viewlet and installs it in the Plone footer. The links and text in the doormat are manageable as content. 
Home-page: https://github.com/collective/Products.Doormat
Author: Kees Hink
Author-email: hink@gw20e.com
License: GPL
Keywords: doormat viewlet plone footer
Platform: UNKNOWN
Classifier: Development Status :: 5 - Production/Stable
Classifier: Environment :: Web Environment
Classifier: Framework :: Plone
Classifier: Framework :: Plone :: 4.3
Classifier: Intended Audience :: End Users/Desktop
Classifier: Operating System :: OS Independent
Classifier: Programming Language :: Python
Classifier: Programming Language :: Python :: 2.7
Classifier: Topic :: Internet
Classifier: Topic :: Scientific/Engineering :: GIS
Classifier: Topic :: Software Development :: Libraries :: Python Modules
